LICENSE
MANIFEST.in
setup.py
select2/__init__.py
select2/conf.py
select2/widgets.py
select2/static/.DS_Store
select2/static/select2/.DS_Store
select2/static/select2/.select2__init.js.un~
select2/static/select2/select2__init.js
select2/static/select2-4.0.2-rc.1/.editorconfig
select2/static/select2-4.0.2-rc.1/.gitignore
select2/static/select2-4.0.2-rc.1/.jshintignore
select2/static/select2-4.0.2-rc.1/.jshintrc
select2/static/select2-4.0.2-rc.1/.travis.yml
select2/static/select2-4.0.2-rc.1/CONTRIBUTING.md
select2/static/select2-4.0.2-rc.1/Gruntfile.js
select2/static/select2-4.0.2-rc.1/LICENSE.md
select2/static/select2-4.0.2-rc.1/README.md
select2/static/select2-4.0.2-rc.1/bower.json
select2/static/select2-4.0.2-rc.1/component.json
select2/static/select2-4.0.2-rc.1/composer.json
select2/static/select2-4.0.2-rc.1/package.json
select2/static/select2-4.0.2-rc.1/select2.jquery.json
select2/static/select2-4.0.2-rc.1/dist/.DS_Store
select2/static/select2-4.0.2-rc.1/dist/css/select2.css
select2/static/select2-4.0.2-rc.1/dist/css/select2.min.css
select2/static/select2-4.0.2-rc.1/dist/js/select2.full.js
select2/static/select2-4.0.2-rc.1/dist/js/select2.full.min.js
select2/static/select2-4.0.2-rc.1/dist/js/select2.js
select2/static/select2-4.0.2-rc.1/dist/js/select2.min.js
select2/static/select2-4.0.2-rc.1/dist/js/i18n/ar.js
select2/static/select2-4.0.2-rc.1/dist/js/i18n/az.js
select2/static/select2-4.0.2-rc.1/dist/js/i18n/bg.js
select2/static/select2-4.0.2-rc.1/dist/js/i18n/ca.js
select2/static/select2-4.0.2-rc.1/dist/js/i18n/cs.js
select2/static/select2-4.0.2-rc.1/dist/js/i18n/da.js
select2/static/select2-4.0.2-rc.1/dist/js/i18n/de.js
select2/static/select2-4.0.2-rc.1/dist/js/i18n/en.js
select2/static/select2-4.0.2-rc.1/dist/js/i18n/es.js
select2/static/select2-4.0.2-rc.1/dist/js/i18n/et.js
select2/static/select2-4.0.2-rc.1/dist/js/i18n/eu.js
select2/static/select2-4.0.2-rc.1/dist/js/i18n/fa.js
select2/static/select2-4.0.2-rc.1/dist/js/i18n/fi.js
twentytab_select2.egg-info/PKG-INFO
twentytab_select2.egg-info/SOURCES.txt
twentytab_select2.egg-info/dependency_links.txt
twentytab_select2.egg-info/requires.txt
twentytab_select2.egg-info/top_level.txt