Metadata-Version: 1.0
Name: twentytab-select2
Version: 0.11
Summary: A django app to customize your admin interface with icons for applications and models and other stuffs
Home-page: https://github.com/20tab/twentytab-select2
Author: 20tab S.r.l.
Author-email: info@20tab.com
License: MIT License
Platform: UNKNOWN
